bernard/__init__.py
bernard/analytics/__init__.py
bernard/analytics/_helpers.py
bernard/analytics/base.py
bernard/analytics/ga/__init__.py
bernard/analytics/ga/_ga.py
bernard/cli/__init__.py
bernard/cli/_base.py
bernard/cli/_live_reload.py
bernard/conf/__init__.py
bernard/conf/default_settings.py
bernard/conf/loader.py
bernard/conf/utils.py
bernard/core/__init__.py
bernard/core/health_check.py
bernard/engine/__init__.py
bernard/engine/fsm.py
bernard/engine/platform.py
bernard/engine/request.py
bernard/engine/responder.py
bernard/engine/state.py
bernard/engine/transition.py
bernard/engine/triggers.py
bernard/i18n/__init__.py
bernard/i18n/_formatter.py
bernard/i18n/intents.py
bernard/i18n/loaders.py
bernard/i18n/translator.py
bernard/i18n/utils.py
bernard/layers/__init__.py
bernard/layers/definitions.py
bernard/layers/stack.py
bernard/media/__init__.py
bernard/media/base.py
bernard/middleware/__init__.py
bernard/middleware/_builtins.py
bernard/middleware/_manager.py
bernard/misc/__init__.py
bernard/misc/main/__init__.py
bernard/misc/main/_base.py
bernard/misc/sheet_sync/__init__.py
bernard/misc/sheet_sync/_base.py
bernard/misc/start_project/__init__.py
bernard/misc/start_project/_base.py
bernard/misc/start_project/files/.editorconfig
bernard/misc/start_project/files/.gitignore
bernard/misc/start_project/files/README.md
bernard/misc/start_project/files/env
bernard/misc/start_project/files/i18n/en/intents.csv
bernard/misc/start_project/files/i18n/en/responses.csv
bernard/misc/start_project/files/manage.py
bernard/misc/start_project/files/requirements.txt
bernard/misc/start_project/files/src/__project_name_snake__/__init__.py
bernard/misc/start_project/files/src/__project_name_snake__/settings.py
bernard/misc/start_project/files/src/__project_name_snake__/states.py
bernard/misc/start_project/files/src/__project_name_snake__/transitions.py
bernard/platforms/__init__.py
bernard/platforms/facebook/__init__.py
bernard/platforms/facebook/helpers.py
bernard-0.7.0.dist-info/LICENSE.md
bernard-0.7.0.dist-info/LICENSE.txt
bernard-0.7.0.dist-info/METADATA
bernard-0.7.0.dist-info/WHEEL
bernard-0.7.0.dist-info/entry_points.txt
bernard-0.7.0.dist-info/RECORD
