Metadata-Version: 2.1
Name: bernard
Version: 0.7.0
Summary: Bot Engine Responding Naturally At Requests Detection
License: AGPL-3.0-or-later
Author: Rémy Sanchez
Author-email: remy.sanchez@hyperthese.net
Requires-Python: >=3.10,<4.0
Classifier: License :: OSI Approved :: GNU Affero General Public License v3 or later (AGPLv3+)
Classifier: Programming Language :: Python :: 3
Classifier: Programming Language :: Python :: 3.10
Classifier: Programming Language :: Python :: 3.11
Classifier: Programming Language :: Python :: 3.12
Requires-Dist: aiohttp (>=3.0,<4.0)
Requires-Dist: babel (>=2.0,<3.0)
Requires-Dist: facepy (>=1.0,<2.0)
Requires-Dist: google-api-python-client
Requires-Dist: google-auth (>=2.0,<3.0)
Requires-Dist: google-auth-oauthlib (>=1.0,<2.0)
Requires-Dist: httpx
Requires-Dist: keyring
Requires-Dist: orjson (>=3.0,<4.0)
Requires-Dist: pyjwt (>=2.0,<3.0)
Requires-Dist: python-dateutil (>=2.0,<3.0)
Requires-Dist: pytz
Requires-Dist: redis (>=4.2.0rc1)
Requires-Dist: rich
Requires-Dist: sentry-sdk
Requires-Dist: unidecode (>=1.0,<2.0)
Requires-Dist: watchdog
